.gitignore
LICENSE
README.rst
circle.yml
setup.cfg
setup.py
aws_parsecf/.gitignore
aws_parsecf/__init__.py
aws_parsecf/common.py
aws_parsecf/conditions.py
aws_parsecf/functions.py
aws_parsecf/loaders.py
aws_parsecf/parser.py
aws_parsecf.egg-info/PKG-INFO
aws_parsecf.egg-info/SOURCES.txt
aws_parsecf.egg-info/dependency_links.txt
aws_parsecf.egg-info/requires.txt
aws_parsecf.egg-info/top_level.txt