Metadata-Version: 1.1
Name: aws-parsecf
Version: 1.1.0
Summary: Parse AWS CloudFormation's intrinsic functions in the template
Home-page: https://github.com/puresec/aws-parsecf
Author: Oded Niv
Author-email: oded.niv@gmail.com
License: MIT
Platform: UNKNOWN
Classifier: License :: OSI Approved :: MIT License
